thunder/__init__.py
thunder/boolpicker.py
thunder/citer.py
thunder/enumpicker.py
thunder/export_conda.py
thunder/fancylogger.py
thunder/filepicker.py
thunder/numberpicker.py
thunder/profiler.py
thunder/repr_dict.py
thunder/stringpicker.py
thunder/thunder_credentials.py
thunder/tools.py
thunder/version.py
thunder/zipit.py
thundertools-0.9.2.dist-info/METADATA
thundertools-0.9.2.dist-info/WHEEL
thundertools-0.9.2.dist-info/top_level.txt
thundertools-0.9.2.dist-info/RECORD
