Metadata-Version: 2.1
Name: thundertools
Version: 0.9.2
Summary: Different tools for working in Python
Home-page: https://github.com/ArnoDeDonder/ThunderTools
Author: Arno De Donder
Author-email: arno.dedonder@hotmail.com
License: MIT
Keywords: python,tools,utility,shell,terminal,scripts,linux,tqdm,zip
Classifier: Programming Language :: Python :: 3.8
Classifier: Programming Language :: Python :: 3.9
Classifier: Programming Language :: Python :: 3.10
Requires-Dist: colorama >=0.4.6
Requires-Dist: setuptools >=65.6.3
Requires-Dist: pyyaml >=6.0.1
